src/__init__.py
src/quip_client.py
src/server.py
src/storage.py
src/tools.py
src/version.py
quip_mcp_server-0.2.0.dist-info/METADATA
quip_mcp_server-0.2.0.dist-info/WHEEL
quip_mcp_server-0.2.0.dist-info/entry_points.txt
quip_mcp_server-0.2.0.dist-info/licenses/LICENSE
quip_mcp_server-0.2.0.dist-info/RECORD
