Metadata-Version: 2.4
Name: quip-mcp-server
Version: 0.2.0
Summary: MCP server for interacting with Quip spreadsheets
Project-URL: Homepage, https://github.com/yourusername/quip-mcp-server
Project-URL: Bug Tracker, https://github.com/yourusername/quip-mcp-server/issues
Author-email: Kane Zhu <me@kane.mx>
License: MIT License
License-File: LICENSE
Requires-Python: >=3.12
Requires-Dist: beautifulsoup4>=4.11.0
Requires-Dist: mcp-python>=0.1.0
Requires-Dist: openpyxl>=3.0.10
Requires-Dist: python-dotenv>=0.20.0
Requires-Dist: requests>=2.28.0
Provides-Extra: dev
Requires-Dist: black>=23.0.0; extra == 'dev'
Requires-Dist: isort>=5.12.0; extra == 'dev'
Requires-Dist: mypy>=1.0.0; extra == 'dev'
Requires-Dist: pytest-asyncio>=0.21.0; extra == 'dev'
Requires-Dist: pytest-cov>=4.1.0; extra == 'dev'
Requires-Dist: pytest>=7.0.0; extra == 'dev'
